gym_rl_book/__init__.py
gym_rl_book/envs/__init__.py
gym_rl_book/envs/multiarmbandit.py
gym_rl_book/envs/tictactoe.py
gym_rl_book/testbeds/__init__.py
gym_rl_book/testbeds/parallel.py
gym_rl_book-0.0.7.dist-info/METADATA
gym_rl_book-0.0.7.dist-info/WHEEL
gym_rl_book-0.0.7.dist-info/top_level.txt
gym_rl_book-0.0.7.dist-info/RECORD
