Metadata-Version: 2.1
Name: gym-rl-book
Version: 0.0.7
Summary: UNKNOWN
Home-page: https://github.com/rl-study/gym-rl-book
Author: void-main
Author-email: voidmain1313113@gmail.com
License: UNKNOWN
Platform: UNKNOWN
Requires-Dist: gym
Requires-Dist: numpy
Requires-Dist: tabulate
Requires-Dist: matplotlib
